nbdev_squ/__init__.py
nbdev_squ/_modidx.py
nbdev_squ/api.py
nbdev_squ/atlaskit-transformer.bundle.js
nbdev_squ/clients.py
nbdev_squ/core.py
nbdev_squ/legacy.py
nbdev_squ-1.3.7.dist-info/LICENSE
nbdev_squ-1.3.7.dist-info/METADATA
nbdev_squ-1.3.7.dist-info/WHEEL
nbdev_squ-1.3.7.dist-info/entry_points.txt
nbdev_squ-1.3.7.dist-info/top_level.txt
nbdev_squ-1.3.7.dist-info/RECORD
