Metadata-Version: 2.2
Name: nbdev-squ
Version: 1.3.7
Summary: Python SIEM Query Utils nbdev edition
Home-page: https://github.com/wagov/nbdev-squ
Author: Adon Metcalfe
Author-email: adonm@fastmail.fm
License: Apache Software License 2.0
Keywords: nbdev jupyter notebook python
Classifier: Development Status :: 4 - Beta
Classifier: Intended Audience :: Developers
Classifier: Natural Language :: English
Classifier: Programming Language :: Python :: 3.12
Classifier: License :: OSI Approved :: Apache Software License
Requires-Python: >=3.12
License-File: LICENSE
Requires-Dist: tenacity
Requires-Dist: platformdirs
Requires-Dist: universal-pathlib
Requires-Dist: adlfs
Requires-Dist: diskcache
Requires-Dist: azure-cli>=2.70
Requires-Dist: azure-monitor-query
Requires-Dist: azure-kusto-data
Requires-Dist: atlassian-python-api
Requires-Dist: abuseipdb_wrapper
Requires-Dist: pysigma
Requires-Dist: pandas
Requires-Dist: dbt-duckdb
Requires-Dist: python-benedict
Requires-Dist: markdown
Requires-Dist: pytenable
Requires-Dist: httpx
Requires-Dist: msticpy[azsentinel]
Provides-Extra: dev
Dynamic: author
Dynamic: author-email
Dynamic: classifier
Dynamic: description
Dynamic: description-content-type
Dynamic: home-page
Dynamic: keywords
Dynamic: license
Dynamic: provides-extra
Dynamic: requires-dist
Dynamic: requires-python
Dynamic: summary
